Workbook

Sheet Read Me
A1: Nightlife Culture / UKDF Fellowship Budget & Delivery Workbook
A2: How to use v0.3 and what changed from v0.2
A3: Version 0.3 | 14 August 2026 | Application working source of truth
A5: This workbook inherits its proposition and language from the Artists Make Great Places master framework.
A7: Control | B7: Current position | D7: Document hierarchy
A8: Budget authority | B8: Phase Budget is the application-facing source of truth. It balances to one flexible £50,000 programme resource. | D8: 1 | E8: Artists Make Great Places master framework | F8: Proposition, canonical language, method, five strands, Why Carly and deck-copy authority | G8: Locked for application drafting | H8: Change by logged decision
A9: Capacity authority | B9: Internal Capacity Test is a sufficiency check only. It does not ringfence founder time or create an external-cost pot. | D9: 2 | E9: UKDF application draft | F9: Full unrestricted narrative before editing to word limits | G9: Next gateway | H9: Inherit from master
A10: Working rate | B10: £500/day appears only where an application field or internal calculation requires a rate. | D10: 3 | E10: Main proposal deck | F10: Persuasive, visual application-facing argument | G10: Copy architecture drafted | H10: Design after copy approval
A11: Delivery window | B11: 10–12 months. Phase outcomes govern delivery; overlap and sequencing can respond to evidence. | D11: 4 | E11: Detailed project-plan deck | F11: Work packages, timeline, scope, budget, boundaries, gates and risks | G11: Copy architecture drafted | H11: Design after copy approval
A12: Confirmed co-funding | B12: ACE £0. Partner cash £0. Partner in-kind £0. No contribution is treated as real until documented. | D12: 5 | E12: Operating plan v0.3 | F12: Detailed delivery and due-diligence source | G12: Aligned | H12: Operational authority
A13: NCVI scope | B13: A proposed shared evidence layer: hypothesis, evidence architecture, low-fidelity prototype, user tests and next-stage technical brief. | D13: 6 | E13: This workbook v0.3 | F13: Numerical and delivery controls | G13: Aligned | H13: Numerical authority
A14: Change control | B14: Decision Log records all material changes from v0.2. The v0.2 files remain preserved.

Sheet Dashboard
A1: UKDF fellowship dashboard
A2: Decision-ready view of budget, scope, capacity and boundaries
A3: Version 0.3 | 14 August 2026 | Application working source of truth
A5: UKDF request | B5: =Assumptions!C6 -> 50000 | C5: Phase budget | D5: ='Phase Budget'!C13 -> 50000 | E5: Variance | F5: =B5-D5 -> 0 | G5: Delivery window | H5: 10–12 months
A6: Working rate if required | B6: =Assumptions!C7 -> 500 | C6: Internal founder-day reference | D6: =Assumptions!C8 -> 52 | E6: Place cases | F6: =Assumptions!C12 -> 2 | G6: Confirmed co-funding | H6: =SUM(Assumptions!C18:C20) -> 0
A7: Substantive conversations | B7: 18–24 | C7: Paid substantial contributions | D7: Up to 15 | E7: Prototype users | F7: 6–10 | G7: ATTTF / WECA first six months | H7: 3 days/week
A8: Primary proposition | B8: Nationally relevant infrastructure that increases hyperlocal power. | C8: NCVI | D8: Proposed shared evidence layer for the cultural life of the night | E8: Step change | F8: Field argument + tested method + investable institution + fundable next phase | G8: Core deliverable through UKDF alone | H8: Yes
A10: Budget by phase
A11: Code | B11: Phase | C11: Envelope | D11: % | F11: Control | G11: Status | H11: Meaning
A12: WP1 | B12: Frame the inquiry | C12: ='Phase Budget'!C6 -> 6000 | D12: ='Phase Budget'!D6 -> 0.12 | F12: Budget balances | G12: Formula | H12: Dashboard variance must equal £0
A13: WP2 | B13: People, scenes and place | C13: ='Phase Budget'!C7 -> 9000 | D13: ='Phase Budget'!D7 -> 0.18 | F13: Founder-day figure | G13: Internal only | H13: 52 days is a sufficiency test, not a public promise
A14: WP3 | B14: Follow the value | C14: ='Phase Budget'!C8 -> 8000 | D14: ='Phase Budget'!D8 -> 0.16 | F14: Day rate | G14: £500 if required | H14: Budget remains phase-based
A15: WP4 | B15: Test what helps | C15: ='Phase Budget'!C9 -> 11000 | D15: ='Phase Budget'!D9 -> 0.22 | F15: ACE / partners | G15: £0 confirmed | H15: Core delivery does not depend on other income
A16: WP5 | B16: Build Nightlife Culture | C16: ='Phase Budget'!C10 -> 7000 | D16: ='Phase Budget'!D10 -> 0.14 | F16: NCVI | G16: Proposed | H16: Prototype and technical brief, not validated national index
A17: WP6 | B17: Integrate and mobilise | C17: ='Phase Budget'!C11 -> 6000 | D17: ='Phase Budget'!D11 -> 0.12 | F17: ATTTF | G17: Separate delivery | H17: WECA supports CBS establishment and Bristol implementation
A18: Programme | B18: Stewardship, access and contingency | C18: ='Phase Budget'!C12 -> 3000 | D18: ='Phase Budget'!D12 -> 0.06
A19: TOTAL | B19: UKDF fellowship | C19: ='Phase Budget'!C13 -> 50000 | D19: ='Phase Budget'!D13 -> 1

Sheet Assumptions
A1: Assumptions & controls
A2: Editable planning inputs; amber cells are live assumptions
A3: Version 0.3 | 14 August 2026 | Application working source of truth
A5: Category | B5: Assumption | C5: Current value | D5: Unit | E5: Basis / status
A6: Programme | B6: UKDF request | C6: 50000 | D6: GBP | E6: Application ceiling
A7: Capacity | B7: Working founder day rate if required | C7: 500 | D7: GBP/day | E7: Carly’s stated working rate
A8: Capacity | B8: Internal founder-days reference | C8: 52 | D8: days | E8: Sufficiency check only
A9: Timeline | B9: Minimum delivery window | C9: 10 | D9: months | E9: Application range
A10: Timeline | B10: Maximum delivery window | C10: 12 | D10: months | E10: Application range
A11: Parallel delivery | B11: ATTTF / WECA commitment in first six months | C11: 3 | D11: days/week | E11: Separate supported commission
A12: Fieldwork | B12: Place cases | C12: 2 | D12: places | E12: Bounded comparative inquiry
A13: Fieldwork | B13: Minimum substantive conversations | C13: 18 | D13: conversations | E13: Across the programme
A14: Fieldwork | B14: Maximum substantive conversations | C14: 24 | D14: conversations | E14: Across the programme
A15: Participation | B15: Maximum paid substantial contributions | C15: 15 | D15: contributors | E15: Payment used when the ask exceeds ordinary engagement
A16: Prototype | B16: Minimum intended-user tests | C16: 6 | D16: users | E16: Low-fidelity test
A17: Prototype | B17: Maximum intended-user tests | C17: 10 | D17: users | E17: Low-fidelity test
... A20: Co-funding | B20: Confirmed partner in-kind value | C20: 0 | D20: GBP | E20: None confirmed

Sheet Work Packages
A1: Work packages
A2: Six distinct delivery jobs beneath five inquiry strands
A3: Version 0.3 | 14 August 2026 | Application working source of truth
A5: Code | B5: Phase | C5: Inquiry strand(s) | D5: Timing | E5: Distinct job | F5: Phase outcome | G5: Decision gate
A6: WP1 | B6: Frame the inquiry | C6: All five | D6: M1–2 | E6: Turn practice and early stakeholder insight into a disciplined inquiry, ethical approach and decision framework | F6: Inquiry frame; stakeholder/evidence maps; protocol; phase gates | G6: G1 — Inquiry ready
A7: WP2 | B7: People, scenes and place | C7: How night makes people / How people make places | D7: M2–5 | E7: Generate field evidence about agency, scenes, spaces and the sonic personality of place | F7: Two place cases; field insight; reusable place lens | G7: G2 — Place evidence sufficient
A8: WP3 | B8: Follow the value | C8: Follow the value | D8: M3–7 | E8: Trace value, power, ownership and reinvestment, with ATTTF as one live learning case | F8: Value-flow maps; restorative investment and advocacy implications | G8: G3 — Value hypotheses usable
A9: WP4 | B9: Test what helps | C9: Test what helps | D9: M5–9 | E9: Develop and test the first expression of the proposed Nightlife Cultural Value Index | F9: Evidence architecture; low-fidelity prototype; 6–10 user tests; technical brief | G9: G4 — Prototype route chosen
A10: WP5 | B10: Build Nightlife Culture | C10: Build the institution | D10: M7–10 | E10: Test the institution, partnerships, offer and income architecture able to carry the work | F10: Institutional proposition; three-part business shape; partner/capability map | G10: G5 — Institution credible
A11: WP6 | B11: Integrate and mobilise | C11: All five | D11: M9–12 | E11: Turn learning into a proposition that others can understand, use, back and develop | F11: Field-backed argument; tested method; investable institution; fundable next phase | G11: G6 — Mobilise next phase
A12: Programme | B12: Stewardship, access and contingency | C12: All five | D12: M1–12 | E12: Protect coordination, accessibility, participant care, data stewardship and evidence-led adaptation | F12: Decision log; programme controls; capacity to respond to discovery | G12: All gates

Sheet Timeline
A1: Timeline & capacity profile
A2: 10–12 month evidence-led programme with deliberate overlap
A3: Version 0.3 | 14 August 2026 | Application working source of truth
A5: Phase | B5: M1 | C5: M2 | D5: M3 | E5: M4 | F5: M5 | G5: M6 | H5: M7 | I5: M8 | J5: M9 | K5: M10 | L5: M11 | M5: M12 | N5: Outcome month
A6: WP1 — Frame | B6: ● | C6: ● | N6: M2
A7: WP2 — People/place | C7: ● | D7: ● | E7: ● | F7: ● | N7: M5
A8: WP3 — Value | D8: ● | E8: ● | F8: ● | G8: ● | H8: ● | N8: M7
A9: WP4 — Test / NCVI | F9: ● | G9: ● | H9: ● | I9: ● | J9: ● | N9: M9
A10: WP5 — Institution | H10: ● | I10: ● | J10: ● | K10: ● | N10: M10
A11: WP6 — Integrate | J11: ● | K11: ● | L11: ● | M11: ● | N11: M12
A12: Stewardship | B12: ● | C12: ● | D12: ● | E12: ● | F12: ● | G12: ● | H12: ● | I12: ● | J12: ● | K12: ● | L12: ● | M12: ● | N12: M12
A15: Internal founder-capacity profile — a planning test, not an application promise
A16: Profile | B16: M1 | C16: M2 | D16: M3 | E16: M4 | F16: M5 | G16: M6 | H16: M7 | I16: M8 | J16: M9 | K16: M10 | L16: M11 | M16: M12 | N16: Total / note
A17: Founder days reference | B17: 4 | C17: 4 | D17: 4 | E17: 4 | F17: 4 | G17: 4 | H17: 5 | I17: 5 | J17: 5 | K17: 5 | L17: 4 | M17: 4 | N17: =SUM(B17:M17) -> 52
A18: ATTTF / WECA days per week | B18: 3 | C18: 3 | D18: 3 | E18: 3 | F18: 3 | G18: 3 | N18: Separate supported commission; first six months
A19: Decision gates | C19: G1 | E19: G2 | G19: G3 | I19: G4 | K19: G5 | M19: G6 | N19: Evidence-led progression

Sheet Phase Budget
A1: Phase budget
A2: One flexible £50,000 programme resource; envelopes are reviewed at decision gates
A3: Version 0.3 | 14 August 2026 | Application working source of truth
A5: Code | B5: Phase | C5: Envelope | D5: % of request | E5: What it must make possible | F5: Review point
A6: WP1 | B6: Frame the inquiry | C6: 6000 | D6: =C6/Assumptions!$C$6 -> 0.12 | E6: Founder capacity; research-design and ethics challenge; evidence and stakeholder mapping; programme setup | F6: G1
A7: WP2 | B7: People, scenes and place | C7: 9000 | D7: =C7/Assumptions!$C$6 -> 0.18 | E7: Founder fieldwork and synthesis; participant contributions; access, travel, facilitation and selected research support | F7: G2
A8: WP3 | B8: Follow the value | C8: 8000 | D8: =C8/Assumptions!$C$6 -> 0.16 | E8: Founder inquiry and synthesis; economic, funding or governance challenge; value-flow development | F8: G3
A9: WP4 | B9: Test what helps | C9: 11000 | D9: =C9/Assumptions!$C$6 -> 0.22 | E9: Founder product/evidence leadership; measurement, data ethics, design and technical expertise; prototype and user testing | F9: G4
A10: WP5 | B10: Build Nightlife Culture | C10: 7000 | D10: =C10/Assumptions!$C$6 -> 0.14 | E10: Founder institutional design; governance, commercial and funding challenge; partnership development | F10: G5
A11: WP6 | B11: Integrate and mobilise | C11: 6000 | D11: =C11/Assumptions!$C$6 -> 0.12 | E11: Founder synthesis; editorial/design support; targeted next-stage technical scoping and mobilisation | F11: G6
A12: Programme | B12: Stewardship, access and contingency | C12: 3000 | D12: =C12/Assumptions!$C$6 -> 0.06 | E12: Coordination, accessibility, participant care, data stewardship and evidence-led contingency | F12: All gates
A13: TOTAL | B13: UKDF fellowship | C13: =SUM(C6:C12) -> 50000 | D13: =C13/Assumptions!$C$6 -> 1 | E13: Balanced to request ceiling | F13: Control

Sheet Internal Capacity Test
A1: Internal capacity sufficiency test
A2: Reference scenarios only; no budget category is ringfenced to founder or external costs
A3: Version 0.3 | 14 August 2026 | Application working source of truth
A5: Rate sensitivity for the 52-day internal reference
A7: Scenario | B7: Reference day rate | C7: Reference days | D7: Founder capacity value | E7: Flexible programme resource remaining in scenario | F7: Meaning
A8: Working application rate | B8: 500 | C8: =Assumptions!$C$8 -> 52 | D8: =B8*C8 -> 26000 | E8: =Assumptions!$C$6-D8 -> 24000 | F8: Carly’s stated rate if a form requires one
A9: Sensitivity | B9: 575 | C9: =Assumptions!$C$8 -> 52 | D9: =B9*C9 -> 29900 | E9: =Assumptions!$C$6-D9 -> 20100 | F9: Internal planning test
A10: Sensitivity | B10: 650 | C10: =Assumptions!$C$8 -> 52 | D10: =B10*C10 -> 33800 | E10: =Assumptions!$C$6-D10 -> 16200 | F10: Internal planning test
A11: Control | B11: =Assumptions!C7 -> 500 | C11: =Assumptions!C8 -> 52 | D11: =B11*C11 -> 26000 | E11: =Assumptions!C6-D11 -> 24000 | F11: All scenarios remain subordinate to the phase budget and outcomes
A14: Illustrative allocation of 52 founder days across programme jobs
A16: Code | B16: Reference days | C16: Planning rationale | E16: Control | F16: Application effect
A17: WP1 | B17: 6 | C17: Intensive framing, mapping and programme setup | E17: 52 days | F17: Shows a credible founder-capacity profile can fit the programme; phase outcomes remain the delivery promise
A18: WP2 | B18: 9 | C18: Field relationships, inquiry and synthesis | E18: £500/day | F18: Used where a rate is required; does not create a ringfenced founder budget line
A19: WP3 | B19: 8 | C19: Value inquiry, ATTTF learning and synthesis | E19: Specialist/direct activity | F19: Commissioned within phase envelopes according to the capability each phase needs
A20: WP4 | B20: 10 | C20: Evidence/product leadership and testing | E20: Gate review | F20: Resource can move between activities when evidence changes the route
A21: WP5 | B21: 8 | C21: Institutional and partnership development | E21: Value for money | F21: Specialist scopes are targeted; larger studies and production builds move to a later funded phase
A22: WP6 | B22: 7 | C22: Synthesis, next phase and mobilisation
A23: Programme | B23: 4 | C23: Stewardship, gates and decision log
A24: TOTAL | B24: =SUM(B17:B23) -> 52 | C24: Internal sufficiency check

Sheet Specialist Inputs
A1: Specialist inputs
A2: Targeted expertise purchased within phase envelopes; scopes remain flexible until the evidence clarifies the need
A3: Version 0.3 | 14 August 2026 | Application working source of truth
A5: Need | B5: Phase | C5: Likely moment | D5: Purpose | E5: Smallest useful scope | F5: Status | G5: Larger work moves to
A6: Research design and ethics | B6: WP1 | C6: G1 | D6: Challenge questions, sampling, participation and claims | E6: Short senior review plus focused revisions | F6: To scope | G6: Later phase only if method risk expands
A7: Place / cultural research | B7: WP2 | C7: G1–G2 | D7: Strengthen comparative design, fieldwork and synthesis | E7: Targeted challenge, access or facilitation | F7: To scope | G7: Additional place cases or national fieldwork
A8: Economic / funding / governance | B8: WP3 | C8: G2–G3 | D8: Interrogate value flows, ownership and restorative investment | E8: Selected questions and value-flow challenge | F8: To scope | G8: Econometrics, ROI/SROI or formal national analysis
A9: Measurement and data ethics | B9: WP4 | C9: G3–G4 | D9: Develop candidate dimensions, evidence standards and safe data principles | E9: Senior design challenge and specification | F9: To scope | G9: Validation, weighting and national benchmarking
A10: Service / information design | B10: WP4 | C10: G4 | D10: Make the evidence architecture tangible and testable | E10: Low-fidelity prototype | F10: To scope | G10: Production UX and platform build
A11: Technical feasibility | B11: WP4 / WP6 | C11: G4 / G6 | D11: Test data/product assumptions and estimate next-stage build | E11: Architecture, dependencies and cost bands | F11: To scope | G11: Software, integrations and ongoing operation
A12: Institutional / legal / commercial | B12: WP5 | C12: G5 | D12: Test governance, partnerships, intellectual assets and income routes | E12: Decision-point advice | F12: To scope | G12: Full implementation and contracted partnerships
A13: Editorial and design | B13: WP6 | C13: G6 | D13: Make field argument and mobilisation materials compelling | E13: Priority application and partner outputs | F13: To scope | G13: Wider campaign and national mobilisation

Sheet Fieldwork
A1: Fieldwork & participation
A2: A bounded programme sized for the £50,000 fellowship
A3: Version 0.3 | 14 August 2026 | Application working source of truth
A5: Activity | B5: Volume | C5: Purpose | D5: Cost treatment | E5: Evidence created | F5: Status | G5: Boundary
A6: Contrasting place cases | B6: =Assumptions!C12 -> 2 | C6: Test people/place thesis beyond one familiar context | D6: Within WP2 phase envelope | E6: Two bounded case records and reusable place lens | F6: To select at G1 | G6: No national sample
A7: Substantive conversations | B7: 18–24 | C7: Gather lived, institutional and specialist knowledge across programme | D7: Founder capacity plus access/facilitation/transcription as needed | E7: Consent record, notes and thematic synthesis | F7: Planned | G7: Across full programme, not per place
A8: Paid substantial contributions | B8: Up to 15 | C8: Recognise participation where the ask exceeds ordinary stakeholder engagement | D8: Within relevant phase envelope | E8: Contributor input and decision trace | F8: Planned | G8: Payment is not assumed for every conversation
A9: NCVI intended-user tests | B9: 6–10 | C9: Challenge usefulness, legitimacy, feasibility and unintended consequences | D9: Within WP4 phase envelope | E9: Test record and prototype revisions | F9: Planned | G9: Qualitative learning, not statistical validation
A10: Rapid evidence review | B10: Bounded | C10: Connect live questions to existing evidence and identify gaps | D10: Founder capacity plus targeted research support | E10: Evidence map and source notes | F10: Planned | G10: No exhaustive systematic review
A11: Accessible existing data | B11: Selected | C11: Test evidence dimensions and feasibility | D11: Within WP3/WP4 envelopes | E11: Data map and technical assumptions | F11: To scope | G11: No national data integration build
A12: Travel, access and participation support | B12: As needed | C12: Enable credible, safe and inclusive participation | D12: Across WP2/WP4 and programme stewardship | E12: Access record and participation learning | F12: To scope | G12: Gate review protects affordability

Sheet Funding Boundaries
A1: Funding boundaries & additionality
A2: Clean roles across UKDF, WECA / A Ticket to the Future, ACE and partners
A3: Version 0.3 | 14 August 2026 | Application working source of truth
A5: Resource | B5: Role | C5: Requested / confirmed | D5: Current status | E5: Boundary | F5: Accounting control
A6: UKDF | B6: Comparative inquiry, transferable learning, NCVI R&D, Nightlife Culture institution and next-stage proposition | C6: =Assumptions!C6 -> 50000 | D6: Requested | E6: Core fellowship is fully deliverable through UKDF alone | F6: Records tagged by work package and phase
A7: WECA / A Ticket to the Future | B7: CBS establishment, governance transition and Bristol implementation | C7: Separate supported commission | D7: In delivery | E7: Does not pay for UKDF comparative inquiry, NCVI or Nightlife Culture institutional R&D | F7: Separate scope, records, outputs and reporting
A8: ACE | B8: Potential future research, sector development, resources or organisational capacity where eligible | C8: =Assumptions!C18 -> 0 | D8: £0 confirmed | E8: Any award extends work through separate scope and governance | F8: Record only after written confirmation
A9: Partners | B9: Potential future access, data, convening, specialist input or cash support | C9: =SUM(Assumptions!C19:C20) -> 0 | D9: £0 confirmed | E9: Core budget does not depend on partner contributions | F9: Document cash/in-kind before inclusion

Sheet Partner Contributions
A1: Partner contributions register
A2: No contribution is treated as confirmed until documented
A3: Version 0.3 | 14 August 2026 | Application working source of truth
A5: Potential contributor | B5: Potential contribution | C5: Cash confirmed | D5: In-kind confirmed value | E5: Evidence of confirmation | F5: Application treatment | G5: Owner | H5: Status
A6: Arts Council England | B6: Potential future research or organisational development | C6: 0 | D6: 0 | E6: None | F6: Excluded from core budget | G6: Carly | H6: Unconfirmed
A7: Place case 1 | B7: Access, convening, local knowledge or data | C7: 0 | D7: 0 | E7: None | F7: Select through G1; no value assumed | G7: Carly | H7: Unconfirmed
A8: Place case 2 | B8: Access, convening, local knowledge or data | C8: 0 | D8: 0 | E8: None | F8: Select through G1; no value assumed | G8: Carly | H8: Unconfirmed
A9: Infrastructure / data partner | B9: Data access, technical challenge or systems insight | C9: 0 | D9: 0 | E9: None | F9: Future enhancement only | G9: Carly | H9: Unconfirmed
A10: University / researcher | B10: Methodological challenge or research collaboration | C10: 0 | D10: 0 | E10: None | F10: Future enhancement only | G10: Carly | H10: Unconfirmed
A11: Sector body | B11: Convening, user testing or mobilisation | C11: 0 | D11: 0 | E11: None | F11: Future enhancement only | G11: Carly | H11: Unconfirmed
A12: TOTAL | B12: Confirmed contributions | C12: =SUM(C6:C11) -> 0 | D12: =SUM(D6:D11) -> 0 | F12: Must remain £0 until evidenced | H12: Control

Sheet Milestones & Gates
A1: Milestones & decision gates
A2: Evidence-led progression across the 10–12 month programme
A3: Version 0.3 | 14 August 2026 | Application working source of truth
A5: Gate | B5: Timing | C5: Decision | D5: Evidence required | E5: Resource decision | F5: Owner | G5: Status
A6: G1 — Inquiry ready | B6: End M2 | C6: Approve scope, cases, ethics and evidence plan | D6: Questions map to decisions; research burden fits resource; boundaries clear | E6: Confirm WP2/WP3 specialist and fieldwork scopes | F6: Carly + adviser | G6: Planned
A7: G2 — Place evidence sufficient | B7: M4–5 | C7: Confirm or adapt cases and thematic focus | D7: Contrasting evidence; credible participation; visible people/place pathways | E7: Adjust access, participation and synthesis support | F7: Carly | G7: Planned
A8: G3 — Value hypotheses usable | B8: M6–7 | C8: Select value and power questions for prototype | D8: Traceable value flows; stakeholder challenge; user implications | E8: Confirm WP4 measurement/design inputs | F8: Carly + specialist | G8: Planned
A9: G4 — Prototype route chosen | B9: M7–8 | C9: Choose smallest useful NCVI expression | D9: Clear users/decisions; feasible data assumptions; ethical and affordable test | E9: Allocate prototype and technical-feasibility resource | F9: Carly + specialist | G9: Planned
A10: G5 — Institution credible | B10: M9–10 | C10: Confirm offer, partnerships and next-stage route | D10: Recognisable proposition; safeguards; capability and income pathways | E10: Confirm institutional and mobilisation inputs | F10: Carly + adviser | G10: Planned
A11: G6 — Mobilise next phase | B11: M11–12 | C11: Approve claims, outputs, cost bands, partners and funding route | D11: Traceability; user value; honest larger-phase scope; named next decisions | E11: Close core programme and issue next-stage brief | F11: Carly | G11: Planned

Sheet Risks & Dependencies
A1: Risks & dependencies
A2: Operational controls for a credible £50,000 fellowship
A3: Version 0.3 | 14 August 2026 | Application working source of truth
A5: ID | B5: Risk / dependency | C5: Likelihood | D5: Impact | E5: Trigger | F5: Control | G5: Gate | H5: Owner | I5: Status
A6: R01 | B6: Founder overload alongside ATTTF / WECA | C6: Medium | D6: High | E6: UKDF phases slip or preparation expands beyond protected capacity | F6: Monthly capacity review; protect phase outputs; targeted support; intensify after M6 | G6: Monthly | H6: Carly | I6: Open
A7: R02 | B7: Scope expands into a national research programme | C7: High | D7: High | E7: More places, surveys, national data or impact measurement enter core phase | F7: Use within/later scope boundary; log extensions as next-phase requirements | G7: G1/G4 | H7: Carly + adviser | I7: Open
A8: R03 | B8: Specialist work is under-scoped | C8: Medium | D8: High | E8: Advice reveals need for substantive research, technical build or legal work | F8: Short discovery scopes; obtain cost bands; move production to next phase | G8: Each commission | H8: Carly | I8: Open
A9: R04 | B9: Participation burden or extractive research | C9: Medium | D9: High | E9: People repeat unpaid accounts without seeing value or influence | F9: Pay substantial contributions; limit asks; return learning; show decision influence | G9: G1–G3 | H9: Carly | I9: Open
A10: R05 | B10: NCVI promise outruns evidence | C10: Medium | D10: High | E10: Language shifts from proposed evidence layer to validated index or product | F10: Canonical definition; prototype only; publish uncertainty and technical next steps | G10: G4 | H10: Carly + specialist | I10: Open
A11: R06 | B11: Funding boundaries blur | C11: Low | D11: High | E11: ATTTF, WECA, UKDF or future funding share activity without attribution | F11: Separate scopes, records and outputs; boundary review at every gate | G11: All gates | H11: Carly | I11: Open
A12: R07 | B12: Institution remains founder-dependent | C12: Medium | D12: Medium | E12: Proposition cannot be carried through partners or specialist capacity | F12: Repeatable method; safeguards; business shape; capability map | G12: G5 | H12: Carly + adviser | I12: Open
A13: R08 | B13: Language and proposition drift | C13: Medium | D13: High | E13: Decks create competing definitions, slogans or method sequences | F13: Master framework authority; decision log; cross-document audit | G13: Every version | H13: Carly | I13: Controlled

Sheet Outputs & Evidence
A1: Outputs, evidence & new capabilities
A2: Phase outcomes are defined by what people can do differently
A3: Version 0.3 | 14 August 2026 | Application working source of truth
A5: Audience / capability | B5: New capability | C5: Tangible evidence | D5: Usefulness test | E5: WP | F5: Timing | G5: Status
A6: Scenes and local advocates | B6: Identify what creates value, gather evidence, frame shared asks and reach decisions or investment | C6: Place lens; evidence prompts; prototype/user journeys; accessible synthesis | D6: Advocates recognise their culture and can identify a practical next action | E6: WP2/WP4/WP6 | F6: M5–12 | G6: Planned
A7: Places | B7: See the cultural life of the night, the conditions sustaining it and the people carrying its future | C7: Two cases; people/place pathway; value-flow maps; NCVI evidence architecture | D7: Place users can identify a decision the evidence improves | E7: WP2–WP4 | F7: M5–9 | G7: Planned
A8: Funders / philanthropy / responsible investors | B8: Find locally legitimate people and propositions with clearer evidence and routes to impact | C8: Value-flow learning; user journey; institutional and partnership proposition | D8: Users can see where investment could strengthen cultural value and agency | E8: WP3–WP6 | F8: M7–12 | G8: Planned
A9: Researchers and sector bodies | B9: Connect local learning to wider evidence, advocacy and methodological development | C9: Inquiry architecture; source/evidence map; technical and ethical brief | D9: Specialist challenge improves claims and next-stage scope | E9: WP1/WP4/WP6 | F9: M2–12 | G9: Planned
A10: Nightlife Culture | B10: Hold and expand the method through a credible institution | C10: Method; institutional proposition; business shape; capability/partner map | D10: Proposition is recognisable, partnerable and less dependent on founder-only delivery | E10: WP5/WP6 | F10: M10–12 | G10: Planned
A11: Field argument | B11: Explain nightlife as infrastructure for agency, talent and place | C11: Synthesis grounded in two place cases, ATTTF learning and wider evidence | D11: Claims are traceable and culturally credible | E11: WP6 | F11: M12 | G11: Planned
A12: Nightlife Cultural Value Index | B12: Use a proposed shared evidence layer to connect local knowledge with action | C12: Candidate dimensions; prototype; 6–10 user tests; technical/ethical next-stage brief | D12: Users see value; limitations and future build are explicit | E12: WP4/WP6 | F12: M9–12 | G12: Planned
A13: Next phase | B13: Move from tested proposition to larger research, validation, technology and/or rollout | C13: Cost bands; dependencies; partner map; funding routes | D13: Scope is honest, investable and does not depend on unconfirmed support | E13: WP6 | F13: M12 | G13: Planned

Sheet Decision Log
A1: Decision log
A2: Material decisions carried into v0.3; v0.2 remains preserved
A3: Version 0.3 | 14 August 2026 | Application working source of truth
A5: ID | B5: Decision area | C5: Decision / application effect | D5: Status | E5: Recorded
A6: D01 | B6: Fellowship architecture | C6: Retain six distinct work packages beneath five inquiry strands; each has its own question, outcome and gate | D6: v0.2 retained | E6: 14 Aug 2026
A7: D02 | B7: Fellowship duration | C7: Use a 10–12 month window with evidence-led overlap | D7: Updated in v0.3 | E7: 14 Aug 2026
A8: D03 | B8: Founder capacity | C8: Keep 52 days as an internal sufficiency test only; phase outcomes govern delivery; £500/day only if required | D8: Updated in v0.3 | E8: 14 Aug 2026
A9: D04 | B9: Budget ceiling | C9: Keep the UKDF request at £50,000 and balance the phase budget to that ceiling | D9: Retained | E9: 14 Aug 2026
A10: D05 | B10: Resource presentation | C10: Present one flexible programme resource creating Carly’s capacity and buying specialist expertise, participation and activity | D10: Updated in v0.3 | E10: 14 Aug 2026
A11: D06 | B11: Research scale | C11: Two place cases; 18–24 conversations; up to 15 paid substantial contributions; 6–10 prototype users | D11: Retained/refined | E11: 14 Aug 2026
A12: D07 | B12: NCVI scope | C12: Proposed shared evidence layer; hypothesis, prototype and technical brief rather than validated national index or platform | D12: Updated in v0.3 | E12: 14 Aug 2026
A13: D08 | B13: ATTTF boundary | C13: Use ATTTF as evidence/live case; WECA supports CBS and Bristol delivery; UKDF supports transferable inquiry and institution | D13: Updated in v0.3 | E13: 14 Aug 2026
A14: D09 | B14: ACE and partner income | C14: Confirmed ACE, partner cash and partner in-kind all remain £0 | D14: Retained | E14: 14 Aug 2026
A15: D10 | B15: Application route | C15: Build unrestricted application narrative first, then edit into main and detailed decks | D15: Retained | E15: 14 Aug 2026
A16: D11 | B16: Deck architecture | C16: Allow a short proposal deck and longer project-plan deck; no imposed 12-slide ceiling | D16: Retained | E16: 14 Aug 2026
... A27: D22 | B27: Capability-led outputs | C27: Frame outputs as new capabilities for advocates, places, funders and Nightlife Culture | D27: New in v0.3 | E27: 14 Aug 2026

Sheet Source Register
A1: Source register
A2: Files and decisions used to consolidate the v0.3 application architecture
A3: Version 0.3 | 14 August 2026 | Application working source of truth
A5: ID | B5: Source | C5: Version / date | D5: Role | E5: Status | F5: Location / note
A6: S01 | B6: Artists Make Great Places master framework and deck copy | C6: v1.0 / 14 Aug 2026 | D6: Proposition and language authority | E6: Current | F6: Created with v0.3 operating materials
A7: S02 | B7: Nightlife Culture — Style Guide | C7: v1.0 / Aug 2026 | D7: Brand, voice, formal definition and writing standards | E7: Current | F7: Expanded style guide
A8: S03 | B8: Nightlife Culture Working Deck | C8: Aug 2026 | D8: Method, delivery ecology, Why Carly, NCVI and business shape | E8: Current reference | F8: Working deck
A9: S04 | B9: UKDF Fellowship Proposal — Artists Make Great Places | C9: v1.1 / Aug 2026 | D9: Most recent pre-consolidation proposal and core thesis | E9: Historical reference | F9: UKDF application folder
A10: S05 | B10: UKDF Fellowship Operating Plan | C10: v0.2 | D10: Prior red-teamed operating baseline | E10: Preserved | F10: Superseded by v0.3
A11: S06 | B11: UKDF Fellowship Budget & Delivery Workbook | C11: v0.2 | D11: Prior numerical baseline | E11: Preserved | F11: Superseded by v0.3
A12: S07 | B12: UKDF pre-application call notes | C12: 24 Jul 2026 | D12: Funder steer on priority use, step change, additionality and movable problem | E12: Current reference | F12: Application notes
A13: S08 | B13: Carly Heath Creative Producer CV | C13: 2026 v2 | D13: Verified founder biography, delivery evidence and awards | E13: Current reference | F13: CV PDF
A14: S09 | B14: BMF Knowledge Base Synthesis | C14: Jun 2026 | D14: ATTTF method, evidence, governance and delivery journey | E14: Current reference | F14: ATTTF knowledge base
